sage_evaluate/__init__.py
sage_evaluate/py.typed
sage_evaluate/wer/.gitattributes
sage_evaluate/wer/README.md
sage_evaluate/wer/app.py
sage_evaluate/wer/requirements.txt
sage_evaluate/wer/wer.py
sage_evaluate/wer/.cache/huggingface/.gitignore
sage_evaluate/wer/.cache/huggingface/download/.gitattributes.lock
sage_evaluate/wer/.cache/huggingface/download/.gitattributes.metadata
sage_evaluate/wer/.cache/huggingface/download/README.md.lock
sage_evaluate/wer/.cache/huggingface/download/README.md.metadata
sage_evaluate/wer/.cache/huggingface/download/app.py.lock
sage_evaluate/wer/.cache/huggingface/download/app.py.metadata
sage_evaluate/wer/.cache/huggingface/download/requirements.txt.lock
sage_evaluate/wer/.cache/huggingface/download/requirements.txt.metadata
sage_evaluate/wer/.cache/huggingface/download/wer.py.lock
sage_evaluate/wer/.cache/huggingface/download/wer.py.metadata
sage_evaluate-0.1.0.dist-info/METADATA
sage_evaluate-0.1.0.dist-info/WHEEL
sage_evaluate-0.1.0.dist-info/RECORD
